MANIFEST.in
README.md
setup.py
datareader/__init__.py
datareader/__main__.py
datareader/definitions.py
datareader.egg-info/PKG-INFO
datareader.egg-info/SOURCES.txt
datareader.egg-info/dependency_links.txt
datareader.egg-info/not-zip-safe
datareader.egg-info/requires.txt
datareader.egg-info/top_level.txt
datareader/data/__init__.py
datareader/data/input/__init__.py
datareader/data/input/stanford/__init__.py
datareader/data/input/stanford/bookstore/__init__.py
datareader/data/input/stanford/bookstore/video0/__init__.py
datareader/data/input/stanford/bookstore/video0/annotations.txt
datareader/data/input/stanford/bookstore/video0/reference.jpg
datareader/data/input/stanford/bookstore/video1/annotations.txt
datareader/data/input/stanford/bookstore/video1/reference.jpg
datareader/data/input/stanford/bookstore/video2/annotations.txt
datareader/data/input/stanford/bookstore/video2/reference.jpg
datareader/data/input/stanford/bookstore/video3/annotations.txt
datareader/data/input/stanford/bookstore/video3/reference.jpg
datareader/data/input/stanford/bookstore/video4/annotations.txt
datareader/data/input/stanford/bookstore/video4/reference.jpg
datareader/data/input/stanford/bookstore/video5/annotations.txt
datareader/data/input/stanford/bookstore/video5/reference.jpg
datareader/data/input/stanford/bookstore/video6/annotations.txt
datareader/data/input/stanford/bookstore/video6/reference.jpg
datareader/data/input/stanford/coupa/video0/annotations.txt
datareader/data/input/stanford/coupa/video0/reference.jpg
datareader/data/input/stanford/coupa/video1/annotations.txt
datareader/data/input/stanford/coupa/video1/reference.jpg
datareader/data/input/stanford/coupa/video2/annotations.txt
datareader/data/input/stanford/coupa/video2/reference.jpg
datareader/data/input/stanford/coupa/video3/annotations.txt
datareader/data/input/stanford/coupa/video3/reference.jpg
datareader/data/input/stanford/deathCircle/video0/annotations.txt
datareader/data/input/stanford/deathCircle/video0/reference.jpg
datareader/data/input/stanford/deathCircle/video1/annotations.txt
datareader/data/input/stanford/deathCircle/video1/reference.jpg
