Metadata-Version: 2.1
Name: datareader
Version: 0.0.7
Summary: Data reader
Home-page: https://github.com/ga74kud/datareader
Author: Michael Hartmann
Author-email: michael.hartmann@v2c2.at
License: GNU GENERAL PUBLIC LICENSE
Platform: UNKNOWN
